{"id":118,"name":"Frame 4624 (5).png","alternativeText":null,"caption":null,"width":1920,"height":1080,"formats":{"small":{"name":"small_Frame 4624 (5).png","hash":"small_Frame_4624_5_2b955fdcc9","ext":".png","mime":"image/png","path":null,"width":500,"height":281,"size":8.56,"sizeInBytes":8563,"url":"/uploads/small_Frame_4624_5_2b955fdcc9.png"},"medium":{"name":"medium_Frame 4624 (5).png","hash":"medium_Frame_4624_5_2b955fdcc9","ext":".png","mime":"image/png","path":null,"width":750,"height":422,"size":14.39,"sizeInBytes":14394,"url":"/uploads/medium_Frame_4624_5_2b955fdcc9.png"},"thumbnail":{"name":"thumbnail_Frame 4624 (5).png","hash":"thumbnail_Frame_4624_5_2b955fdcc9","ext":".png","mime":"image/png","path":null,"width":245,"height":138,"size":3.74,"sizeInBytes":3740,"url":"/uploads/thumbnail_Frame_4624_5_2b955fdcc9.png"},"large":{"name":"large_Frame 4624 (5).png","hash":"large_Frame_4624_5_2b955fdcc9","ext":".png","mime":"image/png","path":null,"width":1000,"height":563,"size":21.24,"sizeInBytes":21241,"url":"/uploads/large_Frame_4624_5_2b955fdcc9.png"}},"hash":"Frame_4624_5_2b955fdcc9","ext":".png","mime":"image/png","size":6.67,"url":"/uploads/Frame_4624_5_2b955fdcc9.png","previewUrl":null,"provider":"local","provider_metadata":null,"folderPath":"/","createdAt":"2024-07-11T15:36:09.676Z","updatedAt":"2024-07-16T18:34:26.538Z"}