{"id":31,"name":"pexels-jopwell-2422293 1.jpg","alternativeText":null,"caption":null,"width":487,"height":414,"formats":{"thumbnail":{"name":"thumbnail_pexels-jopwell-2422293 1.jpg","hash":"thumbnail_pexels_jopwell_2422293_1_00acd3014b","ext":".jpg","mime":"image/jpeg","path":null,"width":184,"height":156,"size":8.65,"sizeInBytes":8652,"url":"/uploads/thumbnail_pexels_jopwell_2422293_1_00acd3014b.jpg"}},"hash":"pexels_jopwell_2422293_1_00acd3014b","ext":".jpg","mime":"image/jpeg","size":35.8,"url":"/uploads/pexels_jopwell_2422293_1_00acd3014b.jpg","previewUrl":null,"provider":"local","provider_metadata":null,"folderPath":"/","createdAt":"2024-05-28T17:03:35.931Z","updatedAt":"2024-07-16T18:33:56.224Z"}